{
  "categories": [
    { "id": 1, "slug": "coffee", "name": "Cà Phê", "nameEn": "Coffee", "icon": "☕", "description": "Espresso-based drinks using premium Arabica & Robusta beans", "color": "#c9a84c", "coverImage": "https://images.unsplash.com/photo-1495474472287-4d71bcdd2085?w=1200&q=80", "beanInfo": "Hạt cà phê Arabica từ Đà Lạt, phối trộn Robusta Tây Nguyên" },
    { "id": 2, "slug": "signature", "name": "Signature", "nameEn": "Signature", "icon": "⭐", "description": "Thức uống đặc trưng của RITA", "color": "#e8c97a", "coverImage": "https://images.unsplash.com/photo-1461023058943-07fcbe16d735?w=1200&q=80", "beanInfo": "Công thức độc quyền, kết hợp nguyên liệu nhập khẩu cao cấp" },
    { "id": 3, "slug": "matcha", "name": "Matcha Latte", "nameEn": "Matcha", "icon": "🍵", "description": "Matcha Uji Nhật Bản hảo hạng, nhập trực tiếp từ Kyoto", "color": "#2d5a27", "coverImage": "https://images.unsplash.com/photo-1536256263959-770b48d82b0a?w=1200&q=80", "beanInfo": "Bột Matcha Ceremonial Grade từ vùng Uji, Kyoto - Nhật Bản" },
    { "id": 4, "slug": "tra-tea", "name": "Trà", "nameEn": "Tea", "icon": "🫖", "description": "Trà trái cây tươi, trà sữa thơm ngon", "color": "#c0392b", "coverImage": "https://images.unsplash.com/photo-1563822249366-3efb23b8e0c9?w=1200&q=80", "beanInfo": "Trà Oolong Đài Loan, trà xanh Thái Nguyên" },
    { "id": 5, "slug": "nuoc-ep", "name": "Nước Ép", "nameEn": "Juice", "icon": "🥤", "description": "Nước ép tươi mỗi ngày, 100% trái cây tự nhiên", "color": "#e67e22", "coverImage": "https://images.unsplash.com/photo-1589733955941-5eeaf752f6dd?w=1200&q=80", "beanInfo": "Trái cây tươi nhập hàng ngày từ vựa rau Rạch Giá" },
    { "id": 6, "slug": "an-sang", "name": "Ăn Sáng", "nameEn": "Breakfast", "icon": "🍳", "description": "Bò né, bánh mì, hủ tiếu - ẩm thực sáng đặc trưng", "color": "#8B4513", "coverImage": "https://images.unsplash.com/photo-1525351484163-7529414344d8?w=1200&q=80", "beanInfo": "Nguyên liệu tươi sống, thịt bò nhập mỗi buổi sáng" },
    { "id": 7, "slug": "dino-kids", "name": "Khu Dino", "nameEn": "Dino Kids Zone", "icon": "🦕", "description": "Khu vui chơi khủng long cho bé, an toàn và thú vị", "color": "#27ae60", "coverImage": "https://images.unsplash.com/photo-1558060370-d644479cb6f7?w=1200&q=80", "beanInfo": "" }
  ],
  "menuItems": [
    { "id": 1, "categoryId": 1, "categorySlug": "coffee", "name": "Cà Phê Đen", "nameEn": "Black Coffee", "price": 25000, "image": "https://images.unsplash.com/photo-1510591509098-f4fdc6d0ff04?w=400&q=80", "description": "Đậm đà, thơm nồng - vị cà phê truyền thống Việt Nam", "tag": "bestseller", "hot": true, "iced": true },
    { "id": 2, "categoryId": 1, "categorySlug": "coffee", "name": "Cà Phê Sữa", "nameEn": "Milk Coffee", "price": 29000, "image": "https://images.unsplash.com/photo-1514432324607-a09d9b4aefdd?w=400&q=80", "description": "Cà phê sữa đặc thơm ngon, béo ngậy", "tag": "popular", "hot": true, "iced": true },
    { "id": 3, "categoryId": 1, "categorySlug": "coffee", "name": "Americano", "nameEn": "Americano", "price": 35000, "image": "https://images.unsplash.com/photo-1551030173-122aabc4489c?w=400&q=80", "description": "Espresso pha loãng với nước nóng, vị thanh nhẹ", "hot": true, "iced": true },
    { "id": 4, "categoryId": 1, "categorySlug": "coffee", "name": "Cappuccino", "nameEn": "Cappuccino", "price": 42000, "image": "https://images.unsplash.com/photo-1534778101976-62847782c213?w=400&q=80", "description": "Espresso với foam sữa dày mịn đặc trưng Ý", "hot": true, "iced": false },
    { "id": 5, "categoryId": 1, "categorySlug": "coffee", "name": "Latte", "nameEn": "Latte", "price": 42000, "image": "https://images.unsplash.com/photo-1561882468-9110e03e0f78?w=400&q=80", "description": "Espresso với sữa tươi đánh bọt mịn, vị béo nhẹ", "hot": true, "iced": true },
    { "id": 6, "categoryId": 1, "categorySlug": "coffee", "name": "Flat White", "nameEn": "Flat White", "price": 45000, "image": "https://images.unsplash.com/photo-1572442388796-11668a67e53d?w=400&q=80", "description": "Ristretto đôi với microfoam sữa, đậm hơn latte", "tag": "new", "hot": true, "iced": false },
    { "id": 7, "categoryId": 2, "categorySlug": "signature", "name": "RITA Special", "nameEn": "RITA Special", "price": 55000, "image": "https://images.unsplash.com/photo-1541167760496-1628856ab772?w=400&q=80", "description": "Thức uống đặc trưng RITA - công thức bí mật của chúng tôi", "tag": "signature", "hot": false, "iced": true },
    { "id": 8, "categoryId": 2, "categorySlug": "signature", "name": "Caramel Cloud", "nameEn": "Caramel Cloud", "price": 52000, "image": "https://images.unsplash.com/photo-1592663527359-cf6642f54cff?w=400&q=80", "description": "Espresso, caramel, foam cheese mây mịn tan chảy", "tag": "bestseller", "hot": false, "iced": true },
    { "id": 9, "categoryId": 2, "categorySlug": "signature", "name": "Taro Cheese Foam", "nameEn": "Taro Cheese Foam", "price": 48000, "image": "https://images.unsplash.com/photo-1558326592-4c2c1c8acac5?w=400&q=80", "description": "Khoai môn tím phủ foam phô mai béo ngậy", "tag": "popular", "hot": false, "iced": true },
    { "id": 10, "categoryId": 2, "categorySlug": "signature", "name": "Brown Sugar Milk Tea", "nameEn": "Brown Sugar Milk Tea", "price": 48000, "image": "https://images.unsplash.com/photo-1558618666-fcd25c85cd64?w=400&q=80", "description": "Trà sữa đường nâu với tiger stripes đặc trưng", "hot": false, "iced": true },
    { "id": 11, "categoryId": 3, "categorySlug": "matcha", "name": "Matcha Latte", "nameEn": "Matcha Latte", "price": 42000, "image": "https://images.unsplash.com/photo-1536256263959-770b48d82b0a?w=400&q=80", "description": "Matcha Uji xay tươi với sữa tươi nguyên kem", "tag": "popular", "hot": true, "iced": true },
    { "id": 12, "categoryId": 3, "categorySlug": "matcha", "name": "Matcha Espresso Fusion", "nameEn": "Matcha Espresso", "price": 48000, "image": "https://images.unsplash.com/photo-1546069901-ba9599a7e63c?w=400&q=80", "description": "Matcha gặp Espresso - sự kết hợp độc đáo East meets West", "tag": "signature", "hot": false, "iced": true },
    { "id": 13, "categoryId": 3, "categorySlug": "matcha", "name": "Cacao Latte", "nameEn": "Cacao Latte", "price": 38000, "image": "https://images.unsplash.com/photo-1542990253-0d0f5be5f0ed?w=400&q=80", "description": "Cacao rang xay thủ công, vị đắng ngọt hài hòa", "hot": true, "iced": true },
    { "id": 14, "categoryId": 3, "categorySlug": "matcha", "name": "Cacao Kenh Vang", "nameEn": "Cacao Kenh Vang", "price": 42000, "image": "https://images.unsplash.com/photo-1606312619070-d48b4c652a52?w=400&q=80", "description": "Cacao đặc biệt pha chế theo phong cách RITA", "tag": "new", "hot": true, "iced": true },
    { "id": 15, "categoryId": 4, "categorySlug": "tra-tea", "name": "Trà Đào Cam Sả", "nameEn": "Peach Lemongrass Tea", "price": 42000, "image": "https://images.unsplash.com/photo-1556679343-c7306c1976bc?w=400&q=80", "description": "Trà đào thơm với cam và sả tươi mát lạnh", "tag": "bestseller", "hot": false, "iced": true },
    { "id": 16, "categoryId": 4, "categorySlug": "tra-tea", "name": "Trà Vải Nhãn", "nameEn": "Lychee Longan Tea", "price": 42000, "image": "https://images.unsplash.com/photo-1563822249366-3efb23b8e0c9?w=400&q=80", "description": "Trà xanh với vải thiều và nhãn tươi", "hot": false, "iced": true },
    { "id": 17, "categoryId": 4, "categorySlug": "tra-tea", "name": "Milk Tea Trân Châu", "nameEn": "Bubble Milk Tea", "price": 39000, "image": "https://images.unsplash.com/photo-1558326592-4c2c1c8acac5?w=400&q=80", "description": "Trà sữa Oolong với trân châu đen dai ngon", "tag": "popular", "hot": false, "iced": true },
    { "id": 18, "categoryId": 4, "categorySlug": "tra-tea", "name": "Trà Tắc Gừng", "nameEn": "Kumquat Ginger Tea", "price": 35000, "image": "https://images.unsplash.com/photo-1597481499750-3e6b22637e12?w=400&q=80", "description": "Trà tắc tươi với gừng tự nhiên, ấm bụng", "hot": true, "iced": true },
    { "id": 19, "categoryId": 5, "categorySlug": "nuoc-ep", "name": "Nước Cam Tươi", "nameEn": "Fresh Orange Juice", "price": 35000, "image": "https://images.unsplash.com/photo-1613478223719-2ab802602423?w=400&q=80", "description": "Cam vắt tươi 100%, không đường không bảo quản", "tag": "healthy", "hot": false, "iced": true },
    { "id": 20, "categoryId": 5, "categorySlug": "nuoc-ep", "name": "Nước Dưa Hấu", "nameEn": "Watermelon Juice", "price": 32000, "image": "https://images.unsplash.com/photo-1589733955941-5eeaf752f6dd?w=400&q=80", "description": "Dưa hấu đỏ ngọt mát, giải nhiệt mùa hè", "hot": false, "iced": true },
    { "id": 21, "categoryId": 5, "categorySlug": "nuoc-ep", "name": "Sinh Tố Xoài", "nameEn": "Mango Smoothie", "price": 38000, "image": "https://images.unsplash.com/photo-1553361371-9b22f78e8b1d?w=400&q=80", "description": "Xoài Cát Hòa Lộc xay mịn với sữa tươi", "tag": "popular", "hot": false, "iced": true },
    { "id": 22, "categoryId": 6, "categorySlug": "an-sang", "name": "Bò Né RITA", "nameEn": "RITA Sizzling Beef", "price": 75000, "image": "https://images.unsplash.com/photo-1558030006-450675393462?w=400&q=80", "description": "Bò né trứng ốp la, pate, xúc xích trên chảo nóng đặc trưng", "tag": "signature", "hot": true, "iced": false },
    { "id": 23, "categoryId": 6, "categorySlug": "an-sang", "name": "Bánh Mì Đặc Biệt", "nameEn": "Special Banh Mi", "price": 35000, "image": "https://images.unsplash.com/photo-1558030006-450675393462?w=400&q=80", "description": "Bánh mì giòn với đầy đủ nhân thịt, pate, rau sống", "tag": "popular", "hot": true, "iced": false },
    { "id": 24, "categoryId": 6, "categorySlug": "an-sang", "name": "Hủ Tiếu Nam Vang", "nameEn": "Nam Vang Noodle Soup", "price": 55000, "image": "https://images.unsplash.com/photo-1569050467447-ce54b3bbc37d?w=400&q=80", "description": "Hủ tiếu nước trong, thịt heo, tôm tươi đậm đà", "tag": "bestseller", "hot": true, "iced": false },
    { "id": 25, "categoryId": 6, "categorySlug": "an-sang", "name": "Trứng Ốp La + Bánh Mì", "nameEn": "Fried Egg + Bread", "price": 28000, "image": "https://images.unsplash.com/photo-1525351484163-7529414344d8?w=400&q=80", "description": "Trứng ốp la vừa chín tới kèm bánh mì giòn", "hot": true, "iced": false }
  ],
  "banners": [
    { "id": 1, "title": "RITA Cafe & Bistro", "subtitle": "Không gian cà phê hiện đại giữa lòng Rạch Giá", "cta": "Khám Phá Menu", "ctaLink": "/menu", "image": "https://images.unsplash.com/photo-1495474472287-4d71bcdd2085?w=1920&q=90", "tag": "Grand Opening" },
    { "id": 2, "title": "Khu Vui Chơi Dino 🦕", "subtitle": "Thiên đường khủng long cho bé - Chỉ 50.000đ/bé", "cta": "Tìm Hiểu Thêm", "ctaLink": "/menu/dino-kids", "image": "https://images.unsplash.com/photo-1558060370-d644479cb6f7?w=1920&q=90", "tag": "Kids Zone" },
    { "id": 3, "title": "Bò Né Đặc Biệt", "subtitle": "Thưởng thức bữa sáng chuẩn vị với Bò Né RITA", "cta": "Xem Menu Sáng", "ctaLink": "/menu/an-sang", "image": "https://images.unsplash.com/photo-1525351484163-7529414344d8?w=1920&q=90", "tag": "Breakfast Special" }
  ],
  "info": {
    "name": "RITA Cafe & Bistro",
    "address": "Rạch Giá, Kiên Giang, Việt Nam",
    "phone": "0xxx xxx xxx",
    "hours": "07:30 AM - 10:30 PM",
    "facebook": "ritacaferachgia",
    "instagram": "ritacafe.rachgia",
    "wifi": "RITA_CAFE / ritacafe2024",
    "parking": "Miễn phí trước quán",
    "dinoPrice": 50000
  },
  "testimonials": [
    { "id": 1, "name": "Nguyễn Minh Anh", "text": "Không gian quán rất đẹp, cà phê ngon, nhân viên thân thiện. Bé nhà mình mê khu Dino lắm!", "rating": 5, "avatar": "https://i.pravatar.cc/100?img=1" },
    { "id": 2, "name": "Trần Văn Hùng", "text": "Bò né RITA chuẩn vị, ăn sáng ở đây rất tuyệt. Sẽ quay lại thường xuyên.", "rating": 5, "avatar": "https://i.pravatar.cc/100?img=3" },
    { "id": 3, "name": "Lê Thị Thu", "text": "Matcha latte ngon nhất Rạch Giá mình từng uống. Quán yên tĩnh, thích hợp làm việc.", "rating": 5, "avatar": "https://i.pravatar.cc/100?img=5" },
    { "id": 4, "name": "Phạm Quốc Bảo", "text": "Decor quán đẹp xuất sắc, chụp ảnh rất ăn. Signature drink của quán rất độc đáo!", "rating": 4, "avatar": "https://i.pravatar.cc/100?img=7" }
  ]
}
